libcomponent/__init__.py
libcomponent/async_clock.py
libcomponent/base_io.py
libcomponent/buffer.py
libcomponent/component.py
libcomponent/encrypted_network.py
libcomponent/encryption.py
libcomponent/network.py
libcomponent/network_utils.py
libcomponent/py.typed
libcomponent/utils.py
libcomponent-0.0.5.dist-info/licenses/LICENSE
libcomponent-0.0.5.dist-info/licenses/LICENSE-THIRD-PARTY
libcomponent-0.0.5.dist-info/METADATA
libcomponent-0.0.5.dist-info/WHEEL
libcomponent-0.0.5.dist-info/top_level.txt
libcomponent-0.0.5.dist-info/RECORD
